[{"t": 0.5, "f": 217.95}, {"t": 0.6, "f": 73.57}, {"t": 0.7, "f": 73.93}, {"t": 0.8, "f": 74.0}, {"t": 0.9, "f": 73.52}, {"t": 1.0, "f": 107.83}, {"t": 1.1, "f": 116.83}, {"t": 1.2, "f": 116.55}, {"t": 1.3, "f": 73.85}, {"t": 1.4, "f": 73.86}, {"t": 1.5, "f": 73.9}, {"t": 1.6, "f": 110.39}, {"t": 1.7, "f": 73.81}, {"t": 1.8, "f": 73.9}, {"t": 1.9, "f": 73.98}, {"t": 2.0, "f": 73.93}, {"t": 2.1, "f": 73.86}, {"t": 2.2, "f": 73.74}, {"t": 2.3, "f": 73.78}, {"t": 2.4, "f": 73.55}, {"t": 2.5, "f": 73.85}, {"t": 2.6, "f": 73.97}, {"t": 2.7, "f": 73.64}, {"t": 2.8, "f": 73.29}, {"t": 2.9, "f": 73.42}, {"t": 3.0, "f": 73.36}, {"t": 3.1, "f": 65.24}, {"t": 3.2, "f": 65.58}, {"t": 3.3, "f": 141.86}, {"t": 3.4, "f": 141.8}, {"t": 3.5, "f": 73.35}, {"t": 3.6, "f": 118.29}, {"t": 3.7, "f": 146.53}, {"t": 3.8, "f": 73.62}, {"t": 3.9, "f": 73.92}, {"t": 4.0, "f": 73.66}, {"t": 4.1, "f": 72.13}, {"t": 4.2, "f": 73.49}, {"t": 4.3, "f": 73.27}, {"t": 4.4, "f": 73.87}, {"t": 4.5, "f": 73.59}, {"t": 4.6, "f": 73.77}, {"t": 4.7, "f": 73.57}, {"t": 4.8, "f": 72.64}, {"t": 4.9, "f": 115.1}, {"t": 5.0, "f": 122.42}, {"t": 5.1, "f": 143.07}, {"t": 5.2, "f": 73.53}, {"t": 5.3, "f": 73.51}, {"t": 5.4, "f": 73.83}, {"t": 5.5, "f": 73.57}, {"t": 5.6, "f": 73.49}, {"t": 5.7, "f": 72.69}, {"t": 5.8, "f": 73.9}, {"t": 5.9, "f": 143.65}, {"t": 6.0, "f": 143.6}, {"t": 6.1, "f": 148.45}, {"t": 6.2, "f": 117.07}, {"t": 6.3, "f": 73.71}, {"t": 6.4, "f": 137.5}, {"t": 6.5, "f": 143.8}, {"t": 6.6, "f": 147.45}, {"t": 6.7, "f": 73.52}, {"t": 6.8, "f": 72.88}, {"t": 6.9, "f": 236.44}, {"t": 7.0, "f": 76.37}, {"t": 7.1, "f": 228.82}, {"t": 7.2, "f": 224.64}, {"t": 7.3, "f": 224.39}, {"t": 7.4, "f": 221.87}, {"t": 7.5, "f": 73.83}, {"t": 7.6, "f": 221.07}, {"t": 7.7, "f": 108.39}, {"t": 7.8, "f": 141.88}, {"t": 7.9, "f": 141.58}, {"t": 8.0, "f": 143.3}, {"t": 8.1, "f": 217.79}, {"t": 8.2, "f": 218.06}, {"t": 8.3, "f": 74.25}, {"t": 8.4, "f": 230.92}, {"t": 8.5, "f": 226.54}, {"t": 8.6, "f": 224.71}, {"t": 8.7, "f": 216.61}, {"t": 8.8, "f": 140.37}, {"t": 8.9, "f": 127.82}, {"t": 9.0, "f": 67.15}, {"t": 9.1, "f": 137.81}, {"t": 9.2, "f": 65.77}, {"t": 9.3, "f": 65.24}, {"t": 9.4, "f": 195.96}, {"t": 9.5, "f": 98.78}, {"t": 9.6, "f": 200.91}, {"t": 9.7, "f": 99.67}, {"t": 9.8, "f": 184.94}, {"t": 9.9, "f": 185.55}, {"t": 10.0, "f": 225.97}, {"t": 10.1, "f": 196.54}, {"t": 10.2, "f": 192.41}, {"t": 10.3, "f": 191.85}, {"t": 10.4, "f": 98.92}, {"t": 10.5, "f": 196.94}, {"t": 10.6, "f": 194.98}, {"t": 10.7, "f": 195.54}, {"t": 10.8, "f": 191.19}, {"t": 10.9, "f": 194.56}, {"t": 11.0, "f": 191.87}, {"t": 11.1, "f": 98.53}, {"t": 11.2, "f": 162.81}, {"t": 11.3, "f": 174.0}, {"t": 11.4, "f": 167.77}, {"t": 11.5, "f": 224.64}, {"t": 11.6, "f": 166.16}, {"t": 11.7, "f": 164.99}, {"t": 11.8, "f": 125.21}, {"t": 11.9, "f": 132.03}, {"t": 12.0, "f": 229.6}, {"t": 12.1, "f": 69.91}, {"t": 12.2, "f": 71.63}, {"t": 12.3, "f": 109.06}, {"t": 12.4, "f": 218.91}, {"t": 12.5, "f": 70.41}, {"t": 12.6, "f": 72.26}, {"t": 12.7, "f": 218.75}, {"t": 12.8, "f": 221.76}, {"t": 12.9, "f": 215.88}, {"t": 13.0, "f": 216.51}, {"t": 13.1, "f": 218.62}, {"t": 13.2, "f": 217.47}, {"t": 13.3, "f": 217.47}, {"t": 13.4, "f": 72.13}, {"t": 13.5, "f": 224.73}, {"t": 13.6, "f": 147.99}, {"t": 13.7, "f": 145.16}, {"t": 13.8, "f": 144.34}, {"t": 13.9, "f": 110.18}, {"t": 14.0, "f": 218.88}, {"t": 14.1, "f": 216.41}, {"t": 14.2, "f": 220.1}, {"t": 14.3, "f": 230.61}, {"t": 14.4, "f": 76.27}, {"t": 14.5, "f": 72.48}, {"t": 14.6, "f": 212.06}, {"t": 14.7, "f": 71.23}, {"t": 14.8, "f": 65.49}, {"t": 14.9, "f": 131.22}, {"t": 15.0, "f": 198.07}, {"t": 15.1, "f": 65.46}, {"t": 15.2, "f": 65.43}, {"t": 15.3, "f": 65.24}, {"t": 15.4, "f": 194.16}, {"t": 15.5, "f": 98.4}, {"t": 15.6, "f": 98.44}, {"t": 15.7, "f": 99.13}, {"t": 15.8, "f": 196.68}, {"t": 15.9, "f": 194.03}, {"t": 16.0, "f": 195.73}, {"t": 16.1, "f": 196.64}, {"t": 16.2, "f": 192.81}, {"t": 16.3, "f": 194.86}, {"t": 16.4, "f": 194.8}, {"t": 16.5, "f": 198.32}, {"t": 16.6, "f": 65.24}, {"t": 16.7, "f": 65.24}, {"t": 16.8, "f": 65.24}, {"t": 16.9, "f": 195.34}, {"t": 17.0, "f": 195.38}, {"t": 17.1, "f": 197.09}, {"t": 17.2, "f": 198.79}, {"t": 17.3, "f": 94.34}, {"t": 17.4, "f": 99.75}, {"t": 17.5, "f": 99.83}, {"t": 17.6, "f": 198.78}, {"t": 17.7, "f": 66.02}, {"t": 17.8, "f": 142.12}, {"t": 17.9, "f": 69.64}, {"t": 18.0, "f": 69.37}, {"t": 18.1, "f": 65.35}, {"t": 18.2, "f": 117.75}, {"t": 18.3, "f": 110.63}, {"t": 18.4, "f": 73.26}, {"t": 18.5, "f": 213.18}, {"t": 18.6, "f": 215.17}, {"t": 18.7, "f": 288.93}, {"t": 18.8, "f": 175.72}, {"t": 18.9, "f": 172.46}, {"t": 19.0, "f": 175.11}, {"t": 19.1, "f": 172.22}, {"t": 19.2, "f": 170.47}, {"t": 19.3, "f": 73.31}, {"t": 19.4, "f": 172.76}, {"t": 19.5, "f": 167.35}, {"t": 19.6, "f": 168.66}, {"t": 19.7, "f": 125.99}, {"t": 19.8, "f": 174.71}, {"t": 19.9, "f": 173.02}, {"t": 20.0, "f": 73.56}, {"t": 20.1, "f": 170.97}, {"t": 20.2, "f": 166.8}, {"t": 20.3, "f": 73.56}, {"t": 20.4, "f": 244.2}, {"t": 20.5, "f": 174.7}, {"t": 20.6, "f": 168.46}, {"t": 20.7, "f": 131.98}, {"t": 20.8, "f": 198.46}, {"t": 20.9, "f": 194.69}, {"t": 21.0, "f": 66.37}, {"t": 21.1, "f": 65.36}, {"t": 21.2, "f": 195.69}, {"t": 21.3, "f": 192.69}, {"t": 21.4, "f": 194.08}, {"t": 21.5, "f": 195.47}, {"t": 21.6, "f": 99.15}, {"t": 21.7, "f": 98.56}, {"t": 21.8, "f": 99.07}, {"t": 21.9, "f": 196.39}, {"t": 22.0, "f": 194.68}, {"t": 22.1, "f": 195.85}, {"t": 22.2, "f": 96.72}, {"t": 22.3, "f": 198.05}, {"t": 22.4, "f": 189.15}, {"t": 22.5, "f": 193.02}, {"t": 22.6, "f": 65.44}, {"t": 22.7, "f": 197.7}, {"t": 22.8, "f": 195.5}, {"t": 22.9, "f": 71.97}, {"t": 23.0, "f": 196.07}, {"t": 23.1, "f": 191.71}, {"t": 23.2, "f": 192.95}, {"t": 23.3, "f": 189.48}, {"t": 23.4, "f": 197.07}, {"t": 23.5, "f": 129.17}, {"t": 23.6, "f": 65.9}, {"t": 23.7, "f": 213.66}, {"t": 23.8, "f": 216.87}, {"t": 23.9, "f": 108.12}, {"t": 24.0, "f": 127.47}, {"t": 24.1, "f": 218.35}, {"t": 24.2, "f": 72.89}, {"t": 24.3, "f": 145.57}, {"t": 24.4, "f": 224.05}, {"t": 24.5, "f": 70.46}, {"t": 24.6, "f": 71.38}, {"t": 24.7, "f": 73.58}, {"t": 24.8, "f": 170.83}, {"t": 24.9, "f": 70.58}, {"t": 25.0, "f": 173.32}, {"t": 25.1, "f": 74.8}, {"t": 25.2, "f": 178.04}, {"t": 25.3, "f": 168.1}, {"t": 25.4, "f": 173.34}, {"t": 25.5, "f": 132.99}, {"t": 25.6, "f": 177.09}, {"t": 25.7, "f": 174.99}, {"t": 25.8, "f": 177.42}, {"t": 25.9, "f": 173.24}, {"t": 26.0, "f": 221.21}, {"t": 26.1, "f": 333.47}, {"t": 26.2, "f": 171.82}, {"t": 26.3, "f": 180.02}, {"t": 26.4, "f": 114.68}, {"t": 26.5, "f": 116.99}, {"t": 26.6, "f": 203.77}, {"t": 26.7, "f": 196.56}, {"t": 26.8, "f": 194.3}, {"t": 26.9, "f": 65.24}, {"t": 27.0, "f": 193.12}, {"t": 27.1, "f": 190.87}, {"t": 27.2, "f": 98.42}, {"t": 27.3, "f": 198.51}, {"t": 27.4, "f": 199.39}, {"t": 27.5, "f": 98.67}, {"t": 27.6, "f": 99.07}, {"t": 27.7, "f": 199.35}, {"t": 27.8, "f": 191.76}, {"t": 27.9, "f": 192.53}, {"t": 28.0, "f": 190.84}, {"t": 28.1, "f": 197.94}, {"t": 28.2, "f": 191.53}, {"t": 28.3, "f": 65.24}, {"t": 28.4, "f": 65.24}, {"t": 28.5, "f": 196.48}, {"t": 28.6, "f": 196.07}, {"t": 28.7, "f": 196.8}, {"t": 28.8, "f": 196.03}, {"t": 28.9, "f": 192.86}, {"t": 29.0, "f": 195.46}, {"t": 29.1, "f": 193.63}, {"t": 29.2, "f": 197.09}, {"t": 29.3, "f": 195.36}, {"t": 29.4, "f": 65.24}, {"t": 29.5, "f": 116.63}, {"t": 29.6, "f": 439.94}, {"t": 29.7, "f": 219.74}, {"t": 29.8, "f": 65.6}, {"t": 29.9, "f": 227.61}, {"t": 30.0, "f": 221.39}, {"t": 30.1, "f": 223.84}, {"t": 30.2, "f": 117.94}, {"t": 30.3, "f": 228.77}, {"t": 30.4, "f": 215.41}, {"t": 30.5, "f": 216.02}, {"t": 30.6, "f": 225.15}, {"t": 30.7, "f": 219.1}, {"t": 30.8, "f": 218.38}, {"t": 30.9, "f": 219.2}, {"t": 31.0, "f": 227.16}, {"t": 31.1, "f": 109.31}, {"t": 31.2, "f": 110.42}, {"t": 31.3, "f": 109.62}, {"t": 31.4, "f": 147.05}, {"t": 31.5, "f": 220.37}, {"t": 31.6, "f": 217.23}, {"t": 31.7, "f": 225.09}, {"t": 31.8, "f": 235.39}, {"t": 31.9, "f": 227.3}, {"t": 32.0, "f": 228.24}, {"t": 32.1, "f": 222.05}, {"t": 32.2, "f": 222.51}, {"t": 32.3, "f": 67.82}, {"t": 32.4, "f": 126.11}, {"t": 32.5, "f": 200.16}, {"t": 32.6, "f": 65.81}, {"t": 32.7, "f": 66.1}, {"t": 32.8, "f": 65.24}, {"t": 32.9, "f": 69.57}, {"t": 33.0, "f": 196.77}, {"t": 33.1, "f": 198.56}, {"t": 33.2, "f": 198.84}, {"t": 33.3, "f": 193.56}, {"t": 33.4, "f": 195.71}, {"t": 33.5, "f": 197.57}, {"t": 33.6, "f": 198.78}, {"t": 33.7, "f": 193.63}, {"t": 33.8, "f": 193.33}, {"t": 33.9, "f": 198.99}, {"t": 34.0, "f": 65.24}, {"t": 34.1, "f": 196.72}, {"t": 34.2, "f": 65.24}, {"t": 34.3, "f": 198.52}, {"t": 34.4, "f": 194.91}, {"t": 34.5, "f": 194.94}, {"t": 34.6, "f": 161.0}, {"t": 34.7, "f": 173.75}, {"t": 34.8, "f": 96.94}, {"t": 34.9, "f": 99.84}, {"t": 35.0, "f": 168.72}, {"t": 35.1, "f": 167.76}, {"t": 35.2, "f": 125.92}, {"t": 35.3, "f": 65.35}, {"t": 35.4, "f": 226.68}, {"t": 35.5, "f": 147.89}, {"t": 35.6, "f": 72.7}, {"t": 35.7, "f": 208.21}, {"t": 35.8, "f": 216.72}, {"t": 35.9, "f": 217.72}, {"t": 36.0, "f": 217.86}, {"t": 36.1, "f": 214.61}, {"t": 36.2, "f": 107.76}, {"t": 36.3, "f": 72.39}, {"t": 36.4, "f": 213.21}, {"t": 36.5, "f": 219.75}, {"t": 36.6, "f": 216.4}, {"t": 36.7, "f": 217.54}, {"t": 36.8, "f": 216.0}, {"t": 36.9, "f": 72.29}, {"t": 37.0, "f": 142.03}, {"t": 37.1, "f": 126.76}, {"t": 37.2, "f": 66.8}, {"t": 37.3, "f": 73.51}, {"t": 37.4, "f": 220.11}, {"t": 37.5, "f": 72.89}, {"t": 37.6, "f": 232.24}, {"t": 37.7, "f": 226.7}, {"t": 37.8, "f": 229.24}, {"t": 37.9, "f": 216.67}, {"t": 38.0, "f": 109.55}, {"t": 38.1, "f": 133.41}, {"t": 38.2, "f": 119.38}, {"t": 38.3, "f": 198.42}, {"t": 38.4, "f": 65.4}, {"t": 38.5, "f": 65.24}, {"t": 38.6, "f": 65.24}, {"t": 38.7, "f": 193.73}, {"t": 38.8, "f": 196.23}, {"t": 38.9, "f": 197.25}, {"t": 39.0, "f": 191.14}, {"t": 39.1, "f": 190.42}, {"t": 39.2, "f": 190.73}, {"t": 39.3, "f": 195.05}, {"t": 39.4, "f": 201.76}, {"t": 39.5, "f": 196.76}, {"t": 39.6, "f": 195.76}, {"t": 39.7, "f": 193.07}, {"t": 39.8, "f": 99.02}, {"t": 39.9, "f": 192.15}, {"t": 40.0, "f": 65.24}, {"t": 40.1, "f": 137.01}, {"t": 40.2, "f": 194.96}, {"t": 40.3, "f": 194.15}, {"t": 40.4, "f": 97.2}, {"t": 40.5, "f": 198.76}, {"t": 40.6, "f": 169.46}, {"t": 40.7, "f": 99.59}, {"t": 40.8, "f": 98.74}, {"t": 40.9, "f": 164.43}, {"t": 41.0, "f": 163.45}, {"t": 41.1, "f": 65.24}, {"t": 41.2, "f": 66.12}, {"t": 41.3, "f": 74.23}, {"t": 41.4, "f": 145.45}, {"t": 41.5, "f": 142.21}, {"t": 41.6, "f": 109.34}, {"t": 41.7, "f": 217.61}, {"t": 41.8, "f": 220.55}, {"t": 41.9, "f": 220.57}, {"t": 42.0, "f": 73.54}, {"t": 42.1, "f": 73.87}, {"t": 42.2, "f": 73.66}, {"t": 42.3, "f": 148.94}, {"t": 42.4, "f": 177.66}, {"t": 42.5, "f": 73.95}, {"t": 42.6, "f": 73.69}, {"t": 42.7, "f": 221.45}, {"t": 42.8, "f": 180.26}, {"t": 42.9, "f": 168.82}, {"t": 43.0, "f": 167.81}, {"t": 43.1, "f": 173.44}, {"t": 43.2, "f": 171.63}, {"t": 43.3, "f": 171.3}, {"t": 43.4, "f": 165.94}, {"t": 43.5, "f": 177.96}, {"t": 43.6, "f": 108.02}, {"t": 43.7, "f": 72.44}, {"t": 43.8, "f": 175.71}, {"t": 43.9, "f": 172.8}, {"t": 44.0, "f": 65.24}, {"t": 44.1, "f": 122.82}, {"t": 44.2, "f": 202.24}, {"t": 44.3, "f": 191.97}, {"t": 44.4, "f": 196.16}, {"t": 44.5, "f": 135.27}, {"t": 44.6, "f": 65.73}, {"t": 44.7, "f": 65.24}, {"t": 44.8, "f": 195.81}, {"t": 44.9, "f": 198.26}, {"t": 45.0, "f": 199.1}, {"t": 45.1, "f": 73.88}, {"t": 45.2, "f": 73.43}, {"t": 45.3, "f": 192.69}, {"t": 45.4, "f": 190.75}, {"t": 45.5, "f": 192.94}, {"t": 45.6, "f": 195.8}, {"t": 45.7, "f": 197.8}, {"t": 45.8, "f": 191.84}, {"t": 45.9, "f": 194.54}, {"t": 46.0, "f": 65.24}, {"t": 46.1, "f": 193.54}, {"t": 46.2, "f": 194.44}, {"t": 46.3, "f": 195.24}, {"t": 46.4, "f": 199.42}, {"t": 46.5, "f": 199.21}, {"t": 46.6, "f": 99.24}, {"t": 46.7, "f": 228.91}, {"t": 46.8, "f": 194.58}, {"t": 46.9, "f": 65.24}, {"t": 47.0, "f": 65.24}, {"t": 47.1, "f": 111.44}, {"t": 47.2, "f": 224.25}, {"t": 47.3, "f": 110.08}, {"t": 47.4, "f": 109.38}, {"t": 47.5, "f": 110.41}, {"t": 47.6, "f": 71.57}, {"t": 47.7, "f": 73.58}, {"t": 47.8, "f": 186.85}, {"t": 47.9, "f": 73.49}, {"t": 48.0, "f": 70.53}, {"t": 48.1, "f": 73.5}, {"t": 48.2, "f": 73.46}, {"t": 48.3, "f": 169.05}, {"t": 48.4, "f": 70.11}, {"t": 48.5, "f": 73.28}, {"t": 48.6, "f": 172.46}, {"t": 48.7, "f": 73.41}, {"t": 48.8, "f": 169.71}, {"t": 48.9, "f": 116.2}, {"t": 49.0, "f": 172.12}, {"t": 49.1, "f": 169.79}, {"t": 49.2, "f": 168.65}, {"t": 49.3, "f": 172.9}, {"t": 49.4, "f": 171.72}, {"t": 49.5, "f": 73.24}, {"t": 49.6, "f": 164.75}, {"t": 49.7, "f": 72.72}, {"t": 49.8, "f": 178.58}, {"t": 49.9, "f": 176.85}, {"t": 50.0, "f": 116.63}, {"t": 50.1, "f": 199.47}, {"t": 50.2, "f": 195.81}, {"t": 50.3, "f": 196.0}, {"t": 50.4, "f": 65.24}, {"t": 50.5, "f": 197.56}, {"t": 50.6, "f": 195.8}, {"t": 50.7, "f": 195.95}, {"t": 50.8, "f": 65.24}, {"t": 50.9, "f": 65.24}, {"t": 51.0, "f": 98.29}, {"t": 51.1, "f": 98.4}, {"t": 51.2, "f": 197.78}, {"t": 51.3, "f": 193.8}, {"t": 51.4, "f": 194.87}, {"t": 51.5, "f": 196.67}, {"t": 51.6, "f": 201.52}, {"t": 51.7, "f": 194.63}, {"t": 51.8, "f": 196.33}, {"t": 51.9, "f": 129.76}, {"t": 52.0, "f": 196.0}, {"t": 52.1, "f": 193.15}, {"t": 52.2, "f": 194.49}, {"t": 52.3, "f": 199.42}, {"t": 52.4, "f": 203.9}, {"t": 52.5, "f": 99.18}, {"t": 52.6, "f": 100.57}, {"t": 52.7, "f": 200.15}, {"t": 52.8, "f": 199.29}, {"t": 52.9, "f": 66.23}, {"t": 53.0, "f": 65.52}, {"t": 53.1, "f": 229.86}, {"t": 53.2, "f": 109.37}, {"t": 53.3, "f": 112.39}, {"t": 53.4, "f": 110.06}, {"t": 53.5, "f": 225.2}, {"t": 53.6, "f": 223.17}, {"t": 53.7, "f": 73.36}, {"t": 53.8, "f": 228.84}, {"t": 53.9, "f": 221.44}, {"t": 54.0, "f": 222.55}, {"t": 54.1, "f": 219.68}, {"t": 54.2, "f": 225.86}, {"t": 54.3, "f": 224.3}, {"t": 54.4, "f": 221.3}, {"t": 54.5, "f": 217.94}, {"t": 54.6, "f": 74.69}, {"t": 54.7, "f": 71.89}, {"t": 54.8, "f": 110.02}, {"t": 54.9, "f": 147.91}, {"t": 55.0, "f": 74.21}, {"t": 55.1, "f": 224.52}, {"t": 55.2, "f": 221.5}, {"t": 55.3, "f": 237.97}, {"t": 55.4, "f": 228.49}, {"t": 55.5, "f": 229.62}, {"t": 55.6, "f": 218.87}, {"t": 55.7, "f": 74.39}, {"t": 55.8, "f": 220.62}, {"t": 55.9, "f": 133.54}, {"t": 56.0, "f": 197.96}, {"t": 56.1, "f": 67.01}, {"t": 56.2, "f": 66.21}, {"t": 56.3, "f": 126.64}, {"t": 56.4, "f": 196.71}, {"t": 56.5, "f": 99.01}, {"t": 56.6, "f": 196.49}, {"t": 56.7, "f": 99.35}, {"t": 56.8, "f": 200.59}, {"t": 56.9, "f": 194.96}, {"t": 57.0, "f": 97.1}, {"t": 57.1, "f": 196.41}, {"t": 57.2, "f": 192.5}, {"t": 57.3, "f": 192.8}, {"t": 57.4, "f": 193.85}, {"t": 57.5, "f": 199.25}, {"t": 57.6, "f": 136.49}, {"t": 57.7, "f": 196.9}, {"t": 57.8, "f": 65.24}, {"t": 57.9, "f": 196.57}, {"t": 58.0, "f": 196.51}, {"t": 58.1, "f": 194.66}, {"t": 58.2, "f": 95.96}, {"t": 58.3, "f": 169.62}, {"t": 58.4, "f": 228.72}, {"t": 58.5, "f": 198.8}, {"t": 58.6, "f": 168.99}, {"t": 58.7, "f": 167.74}, {"t": 58.8, "f": 65.24}, {"t": 58.9, "f": 65.24}, {"t": 59.0, "f": 222.37}, {"t": 59.1, "f": 109.12}, {"t": 59.2, "f": 71.33}, {"t": 59.3, "f": 109.84}, {"t": 59.4, "f": 220.47}, {"t": 59.5, "f": 218.91}, {"t": 59.6, "f": 73.27}, {"t": 59.7, "f": 225.14}, {"t": 59.8, "f": 109.54}, {"t": 59.9, "f": 219.9}, {"t": 60.0, "f": 217.78}, {"t": 60.1, "f": 224.32}, {"t": 60.2, "f": 220.85}, {"t": 60.3, "f": 219.12}, {"t": 60.4, "f": 221.08}, {"t": 60.5, "f": 72.75}, {"t": 60.6, "f": 140.5}, {"t": 60.7, "f": 142.39}, {"t": 60.8, "f": 110.4}, {"t": 60.9, "f": 71.38}, {"t": 61.0, "f": 218.97}, {"t": 61.1, "f": 73.1}, {"t": 61.2, "f": 238.34}, {"t": 61.3, "f": 228.9}, {"t": 61.4, "f": 228.69}, {"t": 61.5, "f": 217.98}, {"t": 61.6, "f": 110.48}, {"t": 61.7, "f": 109.98}, {"t": 61.8, "f": 129.19}, {"t": 61.9, "f": 65.71}, {"t": 62.0, "f": 66.04}, {"t": 62.1, "f": 146.07}, {"t": 62.2, "f": 65.24}, {"t": 62.3, "f": 195.66}, {"t": 62.4, "f": 194.93}, {"t": 62.5, "f": 195.39}, {"t": 62.6, "f": 196.44}, {"t": 62.7, "f": 201.44}, {"t": 62.8, "f": 197.55}, {"t": 62.9, "f": 193.79}, {"t": 63.0, "f": 197.75}, {"t": 63.1, "f": 193.22}, {"t": 63.2, "f": 97.21}, {"t": 63.3, "f": 97.16}, {"t": 63.4, "f": 198.22}, {"t": 63.5, "f": 65.24}, {"t": 63.6, "f": 195.42}, {"t": 63.7, "f": 65.24}, {"t": 63.8, "f": 196.99}, {"t": 63.9, "f": 195.43}, {"t": 64.0, "f": 194.52}, {"t": 64.1, "f": 169.34}, {"t": 64.2, "f": 219.94}, {"t": 64.3, "f": 103.4}, {"t": 64.4, "f": 70.29}, {"t": 64.5, "f": 164.59}, {"t": 64.6, "f": 164.33}, {"t": 64.7, "f": 65.24}, {"t": 64.8, "f": 148.92}, {"t": 64.9, "f": 68.49}, {"t": 65.0, "f": 72.1}, {"t": 65.1, "f": 69.91}, {"t": 65.2, "f": 72.02}, {"t": 65.3, "f": 217.71}, {"t": 65.4, "f": 217.1}, {"t": 65.5, "f": 72.14}, {"t": 65.6, "f": 208.16}, {"t": 65.7, "f": 73.87}, {"t": 65.8, "f": 72.68}, {"t": 65.9, "f": 71.12}, {"t": 66.0, "f": 72.81}, {"t": 66.1, "f": 222.63}, {"t": 66.2, "f": 72.69}, {"t": 66.3, "f": 197.61}, {"t": 66.4, "f": 67.18}, {"t": 66.5, "f": 139.79}, {"t": 66.6, "f": 137.94}, {"t": 66.7, "f": 148.8}, {"t": 66.8, "f": 73.59}, {"t": 66.9, "f": 73.7}, {"t": 67.0, "f": 73.74}, {"t": 67.1, "f": 74.19}, {"t": 67.2, "f": 73.84}, {"t": 67.3, "f": 73.8}, {"t": 67.4, "f": 166.02}, {"t": 67.5, "f": 66.35}, {"t": 67.6, "f": 142.8}, {"t": 67.7, "f": 128.2}, {"t": 67.8, "f": 66.47}, {"t": 67.9, "f": 70.34}, {"t": 68.0, "f": 70.46}, {"t": 68.1, "f": 116.53}, {"t": 68.2, "f": 142.07}, {"t": 68.3, "f": 73.42}, {"t": 68.4, "f": 73.08}, {"t": 68.5, "f": 73.28}, {"t": 68.6, "f": 70.18}, {"t": 68.7, "f": 70.34}, {"t": 68.8, "f": 140.63}, {"t": 68.9, "f": 140.69}, {"t": 69.0, "f": 72.67}]